yhfin/__init__.py
yhfin/yahoo.py
yhfin-0.1.0.dist-info/METADATA
yhfin-0.1.0.dist-info/WHEEL
yhfin-0.1.0.dist-info/RECORD
