Metadata-Version: 2.1
Name: yhfin
Version: 0.1.0
Summary: 
Author: lockermanwxlf
Author-email: 95518889+lockermanwxlf@users.noreply.github.com
Requires-Python: >=3.12,<4.0
Classifier: Programming Language :: Python :: 3
Classifier: Programming Language :: Python :: 3.12
Requires-Dist: fake-useragent (>=1.5.1,<2.0.0)
Requires-Dist: requests (>=2.32.3,<3.0.0)
